fastapi_backstage_sesh/__init__.py
fastapi_backstage_sesh/backends/__init__.py
fastapi_backstage_sesh/backends/base.py
fastapi_backstage_sesh/backends/cookie.py
fastapi_backstage_sesh/backends/in_memory.py
fastapi_backstage_sesh/backstage_config.py
fastapi_backstage_sesh/exceptions.py
fastapi_backstage_sesh/load_config.py
fastapi_backstage_sesh/middleware.py
fastapi_backstage_sesh/session.py
fastapi_backstage_sesh-0.0.2.dist-info/LICENSE
fastapi_backstage_sesh-0.0.2.dist-info/WHEEL
fastapi_backstage_sesh-0.0.2.dist-info/METADATA
fastapi_backstage_sesh-0.0.2.dist-info/RECORD
