Metadata-Version: 2.1
Name: fastapi-backstage-sesh
Version: 0.0.2
Summary: FastAPI Middleware with simple Session implementation, plug n' playable
Home-page: https://github.com/aekasitt/fastapi-backstage-sesh
License: MIT
Keywords: starlette,fastapi,sessions,cookies,samesite,asynchronous
Author: Sitt Guruvanich
Author-email: aekasitt@gmail.com
Requires-Python: >=3.6.2,<4.0.0
Classifier: Environment :: Web Environment
Classifier: Intended Audience :: Developers
Classifier: License :: OSI Approved :: MIT License
Classifier: Operating System :: OS Independent
Classifier: Programming Language :: Python :: 3
Classifier: Programming Language :: Python :: 3.6
Classifier: Programming Language :: Python :: 3.7
Classifier: Programming Language :: Python :: 3.8
Classifier: Programming Language :: Python :: 3.9
Classifier: Topic :: Internet :: WWW/HTTP :: Dynamic Content
Classifier: Topic :: Software Development :: Libraries :: Python Modules
Provides-Extra: examples
Requires-Dist: fastapi (>=0.68.1,<0.69.0)
Requires-Dist: itsdangerous (>=2.0.1,<3.0.0)
Requires-Dist: pydantic (>=1.8.2,<2.0.0)
Requires-Dist: starlette (>=0.14.2,<0.15.0)
Requires-Dist: uvicorn[examples] (>=0.15.0,<0.16.0); extra == "examples"
Project-URL: Repository, https://github.com/aekasitt/fastapi-backstage-sesh
